mapbox_earcut.cpython-39-x86_64-linux-gnu.so
mapbox_earcut-1.0.2.dist-info/LICENSE.md
mapbox_earcut-1.0.2.dist-info/RECORD
mapbox_earcut-1.0.2.dist-info/top_level.txt
mapbox_earcut-1.0.2.dist-info/WHEEL
mapbox_earcut-1.0.2.dist-info/METADATA
