Metadata-Version: 2.1
Name: mapbox_earcut
Version: 1.0.2
Summary: Python bindings for the mapbox earcut C++ polygon             triangulation library.
Home-page: https://github.com/skogler/mapbox_earcut_python
Author: Samuel Kogler
Author-email: samuel.kogler@gmail.com
License: ISC
Project-URL: Source, https://github.com/skogler/mapbox_earcut_python
Project-URL: Original C++ Source, https://github.com/mapbox/earcut.hpp
Requires-Python: >=3.9
License-File: LICENSE.md
Requires-Dist: numpy
Provides-Extra: test
Requires-Dist: pytest; extra == "test"
